odoo/addons/budget_control_expense/README.rst
odoo/addons/budget_control_expense/__init__.py
odoo/addons/budget_control_expense/__manifest__.py
odoo/addons/budget_control_expense/models/__init__.py
odoo/addons/budget_control_expense/models/account_budget_move.py
odoo/addons/budget_control_expense/models/account_move.py
odoo/addons/budget_control_expense/models/account_move_line.py
odoo/addons/budget_control_expense/models/budget_commit_forward.py
odoo/addons/budget_control_expense/models/budget_control.py
odoo/addons/budget_control_expense/models/budget_period.py
odoo/addons/budget_control_expense/models/expense_budget_move.py
odoo/addons/budget_control_expense/models/hr_expense.py
odoo/addons/budget_control_expense/readme/CONTRIBUTORS.md
odoo/addons/budget_control_expense/readme/DESCRIPTION.md
odoo/addons/budget_control_expense/report/__init__.py
odoo/addons/budget_control_expense/report/budget_common_monitoring.py
odoo/addons/budget_control_expense/report/budget_monitor_report.py
odoo/addons/budget_control_expense/security/ir.model.access.csv
odoo/addons/budget_control_expense/static/description/icon.png
odoo/addons/budget_control_expense/static/description/index.html
odoo/addons/budget_control_expense/tests/__init__.py
odoo/addons/budget_control_expense/tests/test_budget_expense.py
odoo/addons/budget_control_expense/views/budget_commit_forward_view.xml
odoo/addons/budget_control_expense/views/budget_control_view.xml
odoo/addons/budget_control_expense/views/budget_period_view.xml
odoo/addons/budget_control_expense/views/expense_budget_move.xml
odoo/addons/budget_control_expense/views/hr_expense_view.xml
odoo/addons/budget_control_expense/wizard/__init__.py
odoo/addons/budget_control_expense/wizard/account_payment_register.py
odoo_addon_budget_control_expense-18.0.1.2.0.dist-info/METADATA
odoo_addon_budget_control_expense-18.0.1.2.0.dist-info/WHEEL
odoo_addon_budget_control_expense-18.0.1.2.0.dist-info/top_level.txt
odoo_addon_budget_control_expense-18.0.1.2.0.dist-info/RECORD
